LICENSE
MANIFEST.in
README.rst
setup.py
django_twilio_sms.egg-info/PKG-INFO
django_twilio_sms.egg-info/SOURCES.txt
django_twilio_sms.egg-info/dependency_links.txt
django_twilio_sms.egg-info/requires.txt
django_twilio_sms.egg-info/top_level.txt
src/__init__.py
src/admin.py
src/decorators.py
src/models.py
src/serializers.py
src/urls.py
src/utils.py
src/views.py