Metadata-Version: 1.1
Name: django-twilio-sms
Version: 0.2
Summary: Twilio integration for SMS-based Django apps
Home-page: https://github.com/nigma/django-twilio-sms
Author: Filip Wasilewski
Author-email: en@ig.ma
License: MIT
Download-URL: https://github.com/nigma/django-twilio-sms/zipball/master
Platform: UNKNOWN
Classifier: Development Status :: 4 - Beta
Classifier: Environment :: Web Environment
Classifier: Framework :: Django
Classifier: Intended Audience :: Developers
Classifier: License :: OSI Approved :: MIT License
Classifier: Operating System :: OS Independent
Classifier: Programming Language :: Python
Classifier: Programming Language :: Python :: 2.6
Classifier: Programming Language :: Python :: 2.7
Classifier: Programming Language :: Python :: 3.2
Classifier: Programming Language :: Python :: 3.3
Classifier: Topic :: Software Development :: Libraries :: Python Modules
